LICENSE
MANIFEST.in
README.md
m2r.py
setup.py
m2r.egg-info/PKG-INFO
m2r.egg-info/SOURCES.txt
m2r.egg-info/dependency_links.txt
m2r.egg-info/entry_points.txt
m2r.egg-info/not-zip-safe
m2r.egg-info/requires.txt
m2r.egg-info/top_level.txt
tests/__init__.py
tests/test_cli.py
tests/test_renderer.py