Metadata-Version: 1.1
Name: m2r
Version: 0.1.8
Summary: Markdown and reStructuredText in a single file.
Home-page: https://github.com/miyakogi/m2r
Author: Hiroyuki Takagi
Author-email: miyako.dev@gmail.com
License: MIT
Keywords: Markdown reStructuredText sphinx-extension
Platform: UNKNOWN
Classifier: Development Status :: 4 - Beta
Classifier: Framework :: Sphinx :: Extension
Classifier: Intended Audience :: Developers
Classifier: License :: OSI Approved :: MIT License
Classifier: Natural Language :: English
Classifier: Programming Language :: Python :: 2
Classifier: Programming Language :: Python :: 2.7
Classifier: Programming Language :: Python :: 3
Classifier: Programming Language :: Python :: 3.4
Classifier: Programming Language :: Python :: 3.5
Classifier: Programming Language :: Python :: 3.6
Classifier: Topic :: Text Processing
